{"data":{"email":"webengage.test.android@zappfresh.com","state":"0","alltax":0.0,"areaid":"556","cartid":"9383C2FE36A639CB7E9BBBA07B0F978A","cityid":"2","saving":0.0,"userid":"b5fc3f74f6052e6","discount":0.0,"expiryat":"2020-06-19 10:12:38","netprice":598.0,"platform":"web","timeslot":"39","cartitems":{"580":{"tax":"0","name":"Chicken Breast Strips + <br> Chicken wings without skin","isnew":"false","price":"598","alltax":0.0,"findex":"NA","instock":"true","catagory":"12","netprice":598.0,"quantity":"250 GMS + 1Kg","taxvalue":0.0,"allsaving":0.0,"netsaving":0.0,"productid":"580","alldiscount":0.0,"netdiscount":0.0,"compareprice":"598","pricewithtax":598.0,"netpricewithtax":598.0,"pricewithouttax":598.0,"comparepriceshow":"false","purchasequantity":"1","netpricewithouttax":598.0}},"channelid":"424","createdat":"2019-10-23 10:12:38","pgpayable":598.0000,"warehouseid":"30","deliverydate":"2019-10-23","walletbalance":"0.0000","deliverycharge":"0.00","netpricewithtax":598.0,"deductfromwallet":0.0000,"netpricewithouttax":598.0,"netpicewithouttaxwhole":598.0,"discountedpricetodisplay":598.0,"labeltext":null},"message":"success","success":true,"errorcode":"00"